checkvist/__init__.py
checkvist/__main__.py
checkvist/py.typed
checkvist/lib/__init__.py
checkvist/lib/client.py
checkvist/lib/models.py
checkvist/lib/httpclient/__init__.py
checkvist/lib/httpclient/client.py
checkvist/lib/httpclient/models.py
checkvist-0.0.1.dev3.dist-info/LICENSE
checkvist-0.0.1.dev3.dist-info/METADATA
checkvist-0.0.1.dev3.dist-info/WHEEL
checkvist-0.0.1.dev3.dist-info/entry_points.txt
checkvist-0.0.1.dev3.dist-info/top_level.txt
checkvist-0.0.1.dev3.dist-info/RECORD
