Metadata-Version: 2.1
Name: checkvist
Version: 0.0.1.dev3
Summary: Checkvist REST API wrapper
Home-page: https://github.com/nuno-andre/checkvist
Author: Nuno André
Author-email: mail@nunoand.re
License: MIT
Project-URL: Source, https://github.com/nuno-andre/checkvist
Project-URL: Tracker, https://github.com/nuno-andre/checkvist/issues
Project-URL: Changelog, https://github.com/nuno-andre/checkvist/master/CHANGELOG.md
Keywords: checkvist,outliner,to-do,todo
Platform: any
Classifier: Development Status :: 2 - Pre-Alpha
Classifier: Intended Audience :: Developers
Classifier: License :: OSI Approved :: MIT License
Classifier: Natural Language :: English
Classifier: Operating System :: OS Independent
Classifier: Programming Language :: Python
Classifier: Programming Language :: Python :: 3.6
Classifier: Programming Language :: Python :: 3.7
Classifier: Programming Language :: Python :: 3.8
Classifier: Programming Language :: Python :: 3.9
Classifier: Topic :: Office/Business :: Scheduling
Classifier: Topic :: Software Development :: Libraries :: Python Modules
Classifier: Topic :: Utilities
Classifier: Typing :: Typed
Requires-Python: >=3.6
Requires-Dist: typer
Requires-Dist: httpx
Requires-Dist: typing-extensions (>=3.7.4) ; python_version < "3.8"
Provides-Extra: docs
Requires-Dist: sphinx ; extra == 'docs'
Requires-Dist: sphinx-rtd-theme ; extra == 'docs'
Provides-Extra: tests
Requires-Dist: pytest ; extra == 'tests'
Requires-Dist: pytest-dependency ; extra == 'tests'
